Metadata-Version: 1.0
Name: matrix-functions
Version: 0.1
Summary: Matrix addition and multiplication
Home-page: UNKNOWN
Author: Christopher Phillips
Author-email: chris@christopher-phillips.com
License: UNKNOWN
Platform: UNKNOWN
